pytest_bdd_md_report/__init__.py
pytest_bdd_md_report/plugin.py
pytest_bdd_md_report/templates/default_report.md.j2
pytest_bdd_md_report-1.0.3.dist-info/METADATA
pytest_bdd_md_report-1.0.3.dist-info/WHEEL
pytest_bdd_md_report-1.0.3.dist-info/entry_points.txt
pytest_bdd_md_report-1.0.3.dist-info/licenses/LICENSE
pytest_bdd_md_report-1.0.3.dist-info/RECORD
