Metadata-Version: 2.4
Name: pytest-bdd-md-report
Version: 1.0.3
Summary: Markdown test report formatter for pytest-bdd with pytest-playwright screenshot support
Project-URL: Homepage, https://github.com/mkt-tokoi/pytest-bdd-md-report
Project-URL: Repository, https://github.com/mkt-tokoi/pytest-bdd-md-report
Project-URL: Issues, https://github.com/mkt-tokoi/pytest-bdd-md-report/issues
Author: mkt-tokoi
License-Expression: MIT
License-File: LICENSE
Keywords: e2e,markdown,playwright,pytest,pytest-bdd,report,testing
Classifier: Development Status :: 4 - Beta
Classifier: Framework :: Pytest
Classifier: Intended Audience :: Developers
Classifier: License :: OSI Approved :: MIT License
Classifier: Operating System :: OS Independent
Classifier: Programming Language :: Python :: 3
Classifier: Programming Language :: Python :: 3.10
Classifier: Programming Language :: Python :: 3.11
Classifier: Programming Language :: Python :: 3.12
Classifier: Programming Language :: Python :: 3.13
Classifier: Programming Language :: Python :: 3.14
Classifier: Topic :: Software Development :: Testing
Requires-Python: >=3.10
Requires-Dist: jinja2>=3.1.0
Requires-Dist: pytest>=7.0.0
Provides-Extra: all
Requires-Dist: pytest-bdd>=6.0.0; extra == 'all'
Requires-Dist: pytest-playwright>=0.4.0; extra == 'all'
Provides-Extra: bdd
Requires-Dist: pytest-bdd>=6.0.0; extra == 'bdd'
Provides-Extra: dev
Requires-Dist: pytest-bdd>=8.1.0; extra == 'dev'
Requires-Dist: pytest-playwright>=0.7.2; extra == 'dev'
Requires-Dist: pytest>=9.0.2; extra == 'dev'
Provides-Extra: playwright
Requires-Dist: pytest-playwright>=0.4.0; extra == 'playwright'
